{"OXEFIT INC": {"DATA SCIENTIST": [{"s": "15-2051", "t": "Data Scientists", "n": 5, "y": [2024, 2025], "o": ["15-2051.01: Business Intelligence Analysts", "15-2051.02: Clinical Data Managers", "15-2051.00: Data Scientists"]}], "DATA  SCIENTIST": [{"s": "15-2051", "t": "Data Scientists", "n": 1, "y": [2024], "o": ["15-2051.01: Business Intelligence Analysts", "15-2051.02: Clinical Data Managers", "15-2051.00: Data Scientists"]}], "SENIOR MEMBER OF TECHNICAL STAFF (SMTS)": [{"s": "15-1252", "t": "Software Developers", "n": 1, "y": [2023], "o": ["15-1252.00: Software Developers"]}], "SENIOR MEMBER TECHNOLOGY STAFF": [{"s": "15-1252", "t": "Software Developers", "n": 1, "y": [2023], "o": ["15-1252.00: Software Developers"]}], "SR MEMBER OF TECHNICAL STAFF": [{"s": "15-1133", "t": "Software Developers, Systems Software", "n": 1, "y": [2022], "o": []}]}, "OXFORD CLINICAL LABORATORY INC": {"LABORATORY TECHNOLOGIST": [{"s": "29-2011", "t": "Medical and Clinical Laboratory Technologists", "n": 1, "y": [2024], "o": []}]}, "OXFORD NANOPORE TECHNOLOGIES INC": {"SENIOR FIELD APPLICATIONS SCIENTIST": [{"s": "19-1029.02", "t": "Molecular and Cellular Biologists", "n": 1, "y": [2024], "o": []}], "SENIOR TECHNICAL APPLICATIONS SCIENTIST": [{"s": "19-1029", "t": "Biological Scientists, All Other", "n": 1, "y": [2024], "o": ["19-1029.01: Bioinformatics Scientists"]}], "TECHNICAL APPLICATIONS MANAGER": [{"s": "19-1029", "t": "Biological Scientists, All Other", "n": 1, "y": [2025], "o": ["19-1029.01: Bioinformatics Scientists"]}], "TECHNICAL APPLICATIONS SCIENTIST": [{"s": "19-1029", "t": "Biological Scientists, All Other", "n": 1, "y": [2023], "o": ["19-1029.01: Bioinformatics Scientists"]}], "FIELD APPLICATIONS SCIENTIST": [{"s": "19-1029.02", "t": "Molecular and Cellular Biologists", "n": 1, "y": [2022], "o": []}]}, "OXFORD THOMPSON DC LEASECO LLC": {"FRONT DESK MANAGER": [{"s": "11-9081", "t": "Lodging Managers", "n": 1, "y": [2024], "o": []}]}, "OXIDE INTERACTIVE INC": {"SENIOR UI ARTIST": [{"s": "27-1024", "t": "Graphic Designers", "n": 1, "y": [2024], "o": []}], "CHARACTER ARTIST": [{"s": "27-1014", "t": "Special Effects Artists and Animators", "n": 1, "y": [2023], "o": []}], "GAMEPLAY ENGINEER": [{"s": "15-1252", "t": "Software Developers", "n": 1, "y": [2023], "o": ["15-1252.00: Software Developers"]}], "TOOLS ENGINEER": [{"s": "15-1252", "t": "Software Developers", "n": 1, "y": [2023], "o": ["15-1252.00: Software Developers"]}], "TECHNICAL ARTIST": [{"s": "27-1014", "t": "Multimedia Artists and Animators", "n": 1, "y": [2022], "o": []}]}, "OXIPITAL AI INC": {"SENIOR MARKETING ANALYST": [{"s": "13-1161", "t": "Market Research Analysts and Marketing Specialists", "n": 1, "y": [2024], "o": ["13-1161.00: Market Research Analysts and Marketing Specialists"]}]}, "OXYA CORPORATION": {"SAP BASIS ADMINISTRATOR": [{"s": "15-1242", "t": "Database Administrators", "n": 2, "y": [2024], "o": ["15-1242.00: Database Administrators"]}], "SAP BASIS CONSULTANT": [{"s": "15-1242", "t": "Database Administrators", "n": 5, "y": [2022, 2023], "o": ["15-1242.00: Database Administrators"]}], "SAP BASIS CONSULTANT (220251)": [{"s": "15-1242", "t": "Database Administrators", "n": 1, "y": [2024], "o": ["15-1242.00: Database Administrators"]}], "SOLUTIONS ARCHITECT": [{"s": "15-1241", "t": "Computer Network Architects", "n": 1, "y": [2024], "o": ["15-1241.00: Computer Network Architects"]}], "ACCOUNT MANAGER": [{"s": "41-9031", "t": "Sales Engineers", "n": 2, "y": [2022, 2025], "o": []}], "SAP BASIS ADMINISTRATOR (8641211)": [{"s": "15-1242", "t": "Database Administrators", "n": 1, "y": [2023], "o": ["15-1242.00: Database Administrators"]}], "SAP BASIS ADMINISTRATOR (8641213)": [{"s": "15-1242", "t": "Database Administrators", "n": 1, "y": [2023], "o": ["15-1242.00: Database Administrators"]}], "SAP BASIS CONSULTANT (8641219)": [{"s": "15-1242", "t": "Database Administrators", "n": 1, "y": [2023], "o": ["15-1242.00: Database Administrators"]}], "SAP BASIS CONSULTANT (8641220)": [{"s": "15-1242", "t": "Database Administrators", "n": 1, "y": [2023], "o": ["15-1242.00: Database Administrators"]}], "SR SAP BASIS ADMINISTRATOR (8641217)": [{"s": "15-1242", "t": "Database Administrators", "n": 1, "y": [2023], "o": ["15-1242.00: Database Administrators"]}], "SR INFRASTRUCTURE ENGINEER (8641225)": [{"s": "15-1243", "t": "Database Architects", "n": 1, "y": [2024], "o": ["15-1243.00: Database Architects"]}], "SAP BASIS ADMINISTRATOR (8641204)": [{"s": "15-1141", "t": "Database Administrators", "n": 1, "y": [2022], "o": []}], "SERVICE DELIVERY MANAGER (SAP BASIS ADMINISTRATOR) 864516": [{"s": "15-1299", "t": "Computer Occupations, All Other", "n": 2, "y": [2022], "o": ["15-1299.08: Computer Systems Engineers/Architects", "15-1299.09: IT Project Managers"]}], "TECHNICAL SPECIALIST (SAP BASIS ADMINISTRATOR) (864498)": [{"s": "15-1141", "t": "Database Administrators", "n": 1, "y": [2022], "o": []}], "SAP BASIS ADMINISTRATOR (8641210)": [{"s": "15-1242", "t": "Database Administrators", "n": 1, "y": [2023], "o": ["15-1242.00: Database Administrators"]}]}, "OXYGEN DEVELOPMENT LLC": {"SUBJECT MATTER EXPERT ENGINEER": [{"s": "17-2112.03", "t": "Manufacturing Engineers", "n": 1, "y": [2024], "o": []}], "SUPPLY CHAIN PLANNING APPLICATIONS ANALYST": [{"s": "15-1121", "t": "Computer Systems Analysts", "n": 2, "y": [2022], "o": []}], "CHEMICAL LABORATORY DIRECTOR": [{"s": "19-2031", "t": "Chemists", "n": 3, "y": [2023, 2025], "o": []}], "FINANCIAL APPLICATIONS ANALYST": [{"s": "15-1211", "t": "Computer Systems Analysts", "n": 1, "y": [2024], "o": ["15-1211.00: Computer Systems Analysts"]}], "ORACLE SUPPLY CHAIN PLANNING ANALYST": [{"s": "15-1211", "t": "Computer Systems Analysts", "n": 1, "y": [2025], "o": ["15-1211.00: Computer Systems Analysts"]}], "PROCESS ENGINEERING MANAGER": [{"s": "11-9041", "t": "Architectural and Engineering Managers", "n": 1, "y": [2022], "o": []}], "CHEMIST": [{"s": "19-2031", "t": "Chemists", "n": 1, "y": [2023], "o": []}]}, "OXFORD AMERICAN LITERARY PROJECT INC": {"ACCOUNTING MANAGER": [{"s": "13-2011", "t": "Accountants and Auditors", "n": 2, "y": [2022, 2025], "o": ["13-2011.00: Accountants and Auditors"]}]}, "OXFORD FINANCE LLC": {"SENIOR DIRECTOR": [{"s": "13-2051", "t": "Financial Analysts", "n": 1, "y": [2022], "o": ["13-2051.00: Financial Analysts"]}]}, "OXFORD INSTRUMENTS ASYLUM RESEARCH INC": {"GLOBAL VICE PRESIDENT OF SALES & MARKETING": [{"s": "11-2021", "t": "Marketing Managers", "n": 1, "y": [2022], "o": ["11-2021.00: Marketing Managers"]}]}, "OXBOW ADVISORS LLC": {"PORTFOLIO SYSTEMS ADMINISTRATION SPECIALIST": [{"s": "13-1199", "t": "Business Operations Specialists, All Other", "n": 2, "y": [2023, 2025], "o": []}]}, "OXEA CORPORATION": {"TECHNICAL MANAGER": [{"s": "11-9199", "t": "Managers, All Other", "n": 1, "y": [2025], "o": []}]}, "OXFAM-AMERICA INC": {"BUSINESS APPLICATIONS MANAGER": [{"s": "15-2051.01", "t": "Business Intelligence Analysts", "n": 1, "y": [2025], "o": []}], "PROGRAM SPECIALIST CLIMATE JUSTICE": [{"s": "11-9151", "t": "Social and Community Service Managers", "n": 3, "y": [2023, 2025], "o": []}], "SENIOR ADVISOR HUMANITARIAN MONITORING EVALUATION ACCOUNT": [{"s": "11-9151", "t": "Social and Community Service Managers", "n": 1, "y": [2025], "o": []}], "SENIOR ADVISOR NEW BUSINESS DEVELOPMENT": [{"s": "11-9151", "t": "Social and Community Service Managers", "n": 2, "y": [2024, 2025], "o": []}], "BUSINESSS APPLICATIONS MANAGER": [{"s": "15-2051.01", "t": "Business Intelligence Analysts", "n": 2, "y": [2023], "o": []}], "CHIEF GENDER JUSTICE AND INCLUSION OFFICER": [{"s": "11-9151", "t": "Social and Community Service Managers", "n": 2, "y": [2024], "o": []}], "SENIOR EVALUATION & LEARNING ADVISOR": [{"s": "11-9151", "t": "Social and Community Service Managers", "n": 1, "y": [2025], "o": []}], "PROGRAM ADVISOR PRIVATE SECTOR DEPARTMENT": [{"s": "11-9151", "t": "Social and Community Service Managers", "n": 1, "y": [2025], "o": []}], "SENIOR PROGRAM ADVISOR GENDER JUSTICE AND INCLUSION HUB": [{"s": "11-9151", "t": "Social and Community Service Managers", "n": 1, "y": [2024], "o": []}], "SENIOR FINANCIAL ANALYST": [{"s": "13-2051", "t": "Financial and Investment Analysts", "n": 3, "y": [2023, 2024, 2025], "o": ["13-2051.00: Financial Analysts"]}], "ASSOCIATE DIRECTOR INCLUSIVE VALUE CHAINS & PRIVATE SECTOR": [{"s": "11-9151", "t": "Social and Community Service Managers", "n": 1, "y": [2023], "o": []}], "SENIOR ADVISOR HUMANITARIAN MEAL": [{"s": "11-9151", "t": "Social and Community Service Managers", "n": 1, "y": [2023], "o": []}], "ADVISOR PVT SECTOR CLIMATE-RESILIENCE & INCL VAL CHAINS": [{"s": "11-9151", "t": "Social and Community Service Managers", "n": 1, "y": [2024], "o": []}], "PROGRAM SPECIALIST PRIVATE SECTOR DEPARTMENT": [{"s": "11-9151", "t": "Social and Community Service Managers", "n": 1, "y": [2022], "o": []}], "SENIOR POLICY ADVISOR GENDER JUSTICE": [{"s": "11-9151", "t": "Social and Community Service Managers", "n": 1, "y": [2022], "o": []}], "ADVISOR HUMANITARIAN MEAL": [{"s": "11-9151", "t": "Social and Community Service Managers", "n": 1, "y": [2022], "o": []}], "DIRECTOR CLIMATE JUSTICE": [{"s": "11-9151", "t": "Social and Community Service Managers", "n": 1, "y": [2022], "o": []}], "SENIOR F2F FUNDRAISING MANAGER": [{"s": "11-9151", "t": "Social and Community Service Managers", "n": 1, "y": [2022], "o": []}], "SENIOR ADVISOR ADVOCACY AND CAMPAIGNS": [{"s": "11-9151", "t": "Social and Community Service Managers", "n": 1, "y": [2023], "o": []}], "SENIOR DISASTER RISK REDUCTION (DRR) AND RESILIENCE MANAGER": [{"s": "11-9151", "t": "Social and Community Service Managers", "n": 1, "y": [2022], "o": []}], "SENIOR EVALUATION AND LEARNING ADVISOR": [{"s": "11-9151", "t": "Social and Community Service Managers", "n": 1, "y": [2022], "o": []}]}, "OXFORD PARENT HOLDINGS LLC": {"SENIOR MEDIA ANALYST": [{"s": "15-2051.01", "t": "Business Intelligence Analysts", "n": 1, "y": [2025], "o": []}]}, "OXIWEAR INC": {"SENIOR UI/UX DESIGNER": [{"s": "27-1024", "t": "Graphic Designers", "n": 1, "y": [2025], "o": []}], "CUSTOMER SUCCESS AND IMPLEMENTATION MANAGER": [{"s": "13-1161", "t": "Market Research Analysts and Marketing Specialists", "n": 1, "y": [2025], "o": ["13-1161.00: Market Research Analysts and Marketing Specialists"]}], "SENIOR UX DESIGNER": [{"s": "15-1255", "t": "Web and Digital Interface Designers", "n": 1, "y": [2025], "o": []}], "COMMERCIALIZATION AND SCIENTIFIC OFFICER": [{"s": "11-2021", "t": "Marketing Managers", "n": 1, "y": [2024], "o": ["11-2021.00: Marketing Managers"]}], "\u00bf\u00bfSENIOR UI/UX DESIGNER": [{"s": "27-1024", "t": "Graphic Designers", "n": 1, "y": [2022], "o": []}]}, "OXOS MEDICAL INC": {"C PLUS PLUS DEVICE ENGINEER": [{"s": "15-1252", "t": "Software Developers", "n": 1, "y": [2025], "o": ["15-1252.00: Software Developers"]}]}, "OXBRIDGE CONSULTING GROUP LLC": {"DEVELOPER": [{"s": "15-1252", "t": "Software Developers", "n": 4, "y": [2023], "o": ["15-1252.00: Software Developers"]}]}, "OXFORD DAY ACADEMY INC": {"MATHEMATICS TEACHER": [{"s": "25-2031", "t": "Secondary School Teachers, Except Special and Career/Technical Education", "n": 3, "y": [2023, 2024], "o": []}]}, "OXFORD GLOBAL RESOURCES LLC": {"SENIOR PEOPLESOFT DEVELOPER": [{"s": "15-1252", "t": "Software Developers", "n": 3, "y": [2022, 2023], "o": ["15-1252.00: Software Developers"]}]}, "OX LABS INC": {"PRODUCT MANAGET": [{"s": "13-1082", "t": "Project Management Specialists", "n": 1, "y": [2024], "o": []}], "PRODUCT MANAGER": [{"s": "11-2021", "t": "Marketing Managers", "n": 1, "y": [2022], "o": ["11-2021.00: Marketing Managers"]}]}, "OXFORD ECONOMICS USA INC": {"DATA VISUALIZATION SPECIALIST [00064772]": [{"s": "15-2051", "t": "Data Scientists", "n": 1, "y": [2024], "o": ["15-2051.01: Business Intelligence Analysts", "15-2051.02: Clinical Data Managers", "15-2051.00: Data Scientists"]}], "ECONOMIST [00064936]": [{"s": "19-3011", "t": "Economists", "n": 1, "y": [2024], "o": []}], "HEAD OF US MACRO CONSULTING [00064935]": [{"s": "19-3011", "t": "Economists", "n": 1, "y": [2024], "o": []}], "JUNIOR DATA ENGINEER [00064671]": [{"s": "15-1243", "t": "Database Architects", "n": 1, "y": [2024], "o": ["15-1243.00: Database Architects"]}], "SENIOR MANAGER DATA SCIENCE AND ENGINEERING [00063031]": [{"s": "11-3021", "t": "Computer and Information Systems Managers", "n": 1, "y": [2024], "o": ["11-3021.00: Computer and Information Systems Managers"]}], "LEAD ECONOMIST - CORPORATE ADVISORY [00080245]": [{"s": "19-3011", "t": "Economists", "n": 1, "y": [2025], "o": []}], "ASSISTANT ECONOMIST [00079287]": [{"s": "19-3011", "t": "Economists", "n": 1, "y": [2025], "o": []}], "DATA ENGINEER[00079954]": [{"s": "15-1243", "t": "Database Architects", "n": 1, "y": [2025], "o": ["15-1243.00: Database Architects"]}], "DATA VISUALIZATION SPECIALIST [00079952]": [{"s": "15-2051", "t": "Data Scientists", "n": 1, "y": [2025], "o": ["15-2051.01: Business Intelligence Analysts", "15-2051.02: Clinical Data Managers", "15-2051.00: Data Scientists"]}], "ECONOMIST [00079960]": [{"s": "19-3011", "t": "Economists", "n": 1, "y": [2025], "o": []}], "ECONOMIST [00060163]": [{"s": "19-3011", "t": "Economists", "n": 1, "y": [2024], "o": []}], "BUSINESS DEVELOPMENT EXECUTIVE AND MARKETING SPECIALIST": [{"s": "13-1161", "t": "Market Research Analysts and Marketing Specialists", "n": 2, "y": [2022, 2023], "o": ["13-1161.00: Market Research Analysts and Marketing Specialists"]}], "ECONOMIST MACRO CONSULTING": [{"s": "19-3011", "t": "Economists", "n": 2, "y": [2022], "o": []}], "LEAD ECONOMIST": [{"s": "19-3011", "t": "Economists", "n": 1, "y": [2022], "o": []}], "ECONOMIST [00049677]": [{"s": "19-3011", "t": "Economists", "n": 1, "y": [2023], "o": []}], "DATA ANALYST [00050869]": [{"s": "15-2051", "t": "Data Scientists", "n": 1, "y": [2023], "o": ["15-2051.01: Business Intelligence Analysts", "15-2051.02: Clinical Data Managers", "15-2051.00: Data Scientists"]}], "ECONOMIST [00049675]": [{"s": "19-3011", "t": "Economists", "n": 1, "y": [2023], "o": []}]}, "OXYGEN INC": {"DIRECTOR OF COMMUNITY ENGAGEMENT": [{"s": "11-2032", "t": "Public Relations Managers", "n": 2, "y": [2024], "o": []}], "DIRECTOR OF PARTNERSHIPS": [{"s": "11-2021", "t": "Marketing Managers", "n": 1, "y": [2024], "o": ["11-2021.00: Marketing Managers"]}], "SENIOR PRODUCT MANAGER": [{"s": "13-1082", "t": "Project Management Specialists", "n": 1, "y": [2024], "o": []}], "DATA ANALYST": [{"s": "15-1199.08", "t": "Business Intelligence Analysts", "n": 1, "y": [2022], "o": []}]}, "OX HILL REALTY LLC": {"SENIOR DEVELOPMENT FINANCE ANALYST": [{"s": "13-2051", "t": "Financial and Investment Analysts", "n": 1, "y": [2025], "o": ["13-2051.00: Financial Analysts"]}]}, "OXBRIDGE HEALTH INC": {"BUSINESS INTELLIGENCE & DATA ENGINEER": [{"s": "15-2051", "t": "Data Scientists", "n": 1, "y": [2025], "o": ["15-2051.01: Business Intelligence Analysts", "15-2051.02: Clinical Data Managers", "15-2051.00: Data Scientists"]}]}, "OXEN LABS INC": {"SOFTWARE ENGINEER": [{"s": "15-1252", "t": "Software Developers", "n": 3, "y": [2024, 2025], "o": ["15-1252.00: Software Developers"]}]}, "OXFORD BIOMEDICA (US) LLC": {"SCIENTIST I": [{"s": "19-2031", "t": "Chemists", "n": 1, "y": [2025], "o": []}], "SCIENTIST I ANALYTICAL DEVELOPMENT": [{"s": "19-1021", "t": "Biochemists and Biophysicists", "n": 1, "y": [2025], "o": []}], "RESEARCH ASSOCIATE": [{"s": "19-1021", "t": "Biochemists and Biophysicists", "n": 1, "y": [2024], "o": []}], "SCIENTIST II": [{"s": "19-1021", "t": "Biochemists and Biophysicists", "n": 2, "y": [2024], "o": []}]}, "OXFORD BIOTHERAPEUTICS INC": {"RESEARCH ASSOCIATE": [{"s": "19-1021", "t": "Biochemists and Biophysicists", "n": 2, "y": [2025], "o": []}]}, "OXFORD CAPITAL GROUP LLC": {"DIRECTOR OF OPERATIONS": [{"s": "11-1021", "t": "General and Operations Managers", "n": 1, "y": [2025], "o": []}]}, "OXFORD CAPITAL LLC": {"DIRECTOR OF OPERATIONS": [{"s": "11-1021", "t": "General and Operations Managers", "n": 1, "y": [2025], "o": []}]}, "OXFORD CONTRACTING CO INC": {"SBDI SPECIALIST": [{"s": "13-1199.05", "t": "Sustainability Specialists", "n": 1, "y": [2025], "o": []}], "STRATEGIC MARKETING AND GROWTH ASSOCIATE": [{"s": "13-1161", "t": "Market Research Analysts and Marketing Specialists", "n": 1, "y": [2025], "o": ["13-1161.00: Market Research Analysts and Marketing Specialists"]}], "STRATEGIC MARKETING & ANALYTICS SPECIALIST": [{"s": "13-1161", "t": "Market Research Analysts and Marketing Specialists", "n": 1, "y": [2022], "o": ["13-1161.00: Market Research Analysts and Marketing Specialists"]}]}, "OXFORD LIFE INSURANCE CO": {"INVESTMENT ACCOUNTANT": [{"s": "13-2051", "t": "Financial and Investment Analysts", "n": 1, "y": [2025], "o": ["13-2051.00: Financial Analysts"]}]}, "OXIUM LLC": {"CHIEF INTERNATIONAL DEVELOPMENT OFFICER": [{"s": "11-1021", "t": "General and Operations Managers", "n": 2, "y": [2025], "o": []}]}, "OXMAINT INC": {"SOFTWARE ENGINEER": [{"s": "15-1252", "t": "Software Developers", "n": 1, "y": [2025], "o": ["15-1252.00: Software Developers"]}]}, "OXMIQ LABS INC": {"SOFTWARE PRODUCT MANAGER": [{"s": "15-1252", "t": "Software Developers", "n": 1, "y": [2025], "o": ["15-1252.00: Software Developers"]}]}, "OXYGY CONSULTING INC": {"DIGITAL TRANSFORMATION MANAGEMENT ANALYST": [{"s": "13-1111", "t": "Management Analysts", "n": 1, "y": [2025], "o": ["13-1111.00: Management Analysts"]}]}, "OXFORD STRATEGIC LEGAL ADVISORS": {"SENIOR DATA SCIENTIST": [{"s": "15-2051", "t": "Data Scientists", "n": 1, "y": [2025], "o": ["15-2051.01: Business Intelligence Analysts", "15-2051.02: Clinical Data Managers", "15-2051.00: Data Scientists"]}]}, "OXBOW CALCINING LLC": {"CHEMIST": [{"s": "19-2031", "t": "Chemists", "n": 1, "y": [2024], "o": []}]}, "OXFORD COMMUNICATIONS INC": {"MEDIA AND INFORMATION SYSTEMS ANALYST": [{"s": "13-1161", "t": "Market Research Analysts and Marketing Specialists", "n": 1, "y": [2024], "o": ["13-1161.00: Market Research Analysts and Marketing Specialists"]}]}, "OXFORD INTELLIGENT ENERGY CO LTD": {"MARKET ANALYST": [{"s": "13-1161", "t": "Market Research Analysts and Marketing Specialists", "n": 1, "y": [2024], "o": ["13-1161.00: Market Research Analysts and Marketing Specialists"]}], "PUBLIC RELATIONS SPECIALIST": [{"s": "27-3031", "t": "Public Relations Specialists", "n": 1, "y": [2023], "o": []}]}, "OXFORD LTD": {"PRODUCT DESIGNER": [{"s": "27-1021", "t": "Commercial and Industrial Designers", "n": 1, "y": [2024], "o": []}]}, "OXFORD MUSIC ACADEMY LLC": {"PIANO TEACHER": [{"s": "25-1121", "t": "Art, Drama, and Music Teachers, Postsecondary", "n": 1, "y": [2024], "o": []}]}, "OXFORD NANOIMAGING INC": {"SENIOR SOFTWARE ENGINEER": [{"s": "15-1252", "t": "Software Developers", "n": 1, "y": [2024], "o": ["15-1252.00: Software Developers"]}], "SENIOR CHEMIST": [{"s": "19-2031", "t": "Chemists", "n": 1, "y": [2023], "o": []}]}, "OXFORD PHARMAGENESIS INC": {"SENIOR MEDICAL WRITER": [{"s": "27-3042", "t": "Technical Writers", "n": 1, "y": [2024], "o": []}], "MEDICAL WRITER": [{"s": "27-3042", "t": "Technical Writers", "n": 1, "y": [2022], "o": []}]}, "OXFORD ROAD": {"SR DATA ENGINEER": [{"s": "15-2051", "t": "Data Scientists", "n": 1, "y": [2024], "o": ["15-2051.01: Business Intelligence Analysts", "15-2051.02: Clinical Data Managers", "15-2051.00: Data Scientists"]}]}, "OXFORD I ASSET MANAGEMENT USA INC": {"ASSOCIATE CREDIT INVESTMENTS - KBGFJG309101-3": [{"s": "13-2051", "t": "Financial and Investment Analysts", "n": 1, "y": [2025], "o": ["13-2051.00: Financial Analysts"]}], "ASSOCIATE DIRECTOR INVESTMENTS": [{"s": "13-2051", "t": "Financial Analysts", "n": 2, "y": [2022], "o": ["13-2051.00: Financial Analysts"]}]}, "OXFORD ALLOYS INC": {"STRATEGIC PLANNER": [{"s": "13-1161", "t": "Market Research Analysts and Marketing Specialists", "n": 2, "y": [2022, 2023], "o": ["13-1161.00: Market Research Analysts and Marketing Specialists"]}]}, "OXFORD INSTRUMENTS X-RAY TECHNOLOGY INC": {"ELECTRICAL ENGINEER": [{"s": "17-2071", "t": "Electrical Engineers", "n": 1, "y": [2023], "o": ["17-2071.00: Electrical Engineers"]}]}, "OXNARD MANOR LP": {"OCCUPATIONAL THERAPIST": [{"s": "29-1122", "t": "Occupational Therapists", "n": 1, "y": [2023], "o": []}]}, "OXYCARBON US INC": {"CHIEF EXECUTIVE OFFICER": [{"s": "11-1011", "t": "Chief Executives", "n": 1, "y": [2023], "o": []}], "GLOBAL BUSINESS DEVELOPMENT EXECUTIVE": [{"s": "13-1161", "t": "Market Research Analysts and Marketing Specialists", "n": 1, "y": [2022], "o": ["13-1161.00: Market Research Analysts and Marketing Specialists"]}]}, "OXCO INC": {"SR PRODUCT ENGINEER": [{"s": "41-9031", "t": "Sales Engineers", "n": 1, "y": [2024], "o": []}]}, "OXFORD BIOMEDICA SOLUTIONS LLC": {"SR RESEARCH ASSOCIATE II ANALYTICAL DEVELOPMENT": [{"s": "19-1021", "t": "Biochemists and Biophysicists", "n": 1, "y": [2022], "o": []}]}, "OXYION CA LLC": {"LOGISTICS ENGINEER": [{"s": "13-1081.01", "t": "Logistics Engineers", "n": 1, "y": [2023], "o": []}]}, "OXAGILE LLC": {"SALES ENGINEER": [{"s": "41-9031", "t": "Sales Engineers", "n": 1, "y": [2023], "o": []}]}, "OXBOW INDUSTRIES LLC": {"MANAGING DIRECTOR": [{"s": "11-9041", "t": "Architectural and Engineering Managers", "n": 1, "y": [2023], "o": []}]}, "OXFORD BUILDERS INCORPORATED": {"CIVIL ENGINEER": [{"s": "17-2051", "t": "Civil Engineers", "n": 1, "y": [2023], "o": ["17-2051.00: Civil Engineers"]}]}}