{"WQW INC": {"GRAPHIC DESIGNER": [{"s": "27-1024", "t": "Graphic Designers", "n": 3, "y": [2025], "o": []}], "MARKET RESEARCH AND MARKETING SPECIALIST": [{"s": "13-1161", "t": "Market Research Analysts and Marketing Specialists", "n": 3, "y": [2025], "o": ["13-1161.00: Market Research Analysts and Marketing Specialists"]}]}, "WQB ARCHITECTURE PLLC": {"INTERMEDIATE": [{"s": "27-1029", "t": "Designers, All Other", "n": 1, "y": [2024], "o": []}], "INTERMEDIATE DESIGNER": [{"s": "27-1029", "t": "Designers, All Other", "n": 1, "y": [2024], "o": []}], "PROJECT MANAGER": [{"s": "17-1011", "t": "Architects, Except Landscape and Naval", "n": 1, "y": [2022], "o": []}], "JUNIOR DESIGNER": [{"s": "27-1029", "t": "Designers, All Other", "n": 1, "y": [2023], "o": []}]}, "WQS FOOD VERIFICATION LLC": {"FOOD SAFETY AUDITOR": [{"s": "19-1012", "t": "Food Scientists and Technologists", "n": 3, "y": [2022, 2024], "o": []}]}}